gcsa/__init__.py
gcsa/_resource.py
gcsa/acl.py
gcsa/attachment.py
gcsa/attendee.py
gcsa/calendar.py
gcsa/conference.py
gcsa/event.py
gcsa/free_busy.py
gcsa/google_calendar.py
gcsa/person.py
gcsa/recurrence.py
gcsa/reminders.py
gcsa/settings.py
gcsa/_services/__init__.py
gcsa/_services/acl_service.py
gcsa/_services/authentication.py
gcsa/_services/base_service.py
gcsa/_services/calendar_lists_service.py
gcsa/_services/calendars_service.py
gcsa/_services/colors_service.py
gcsa/_services/events_service.py
gcsa/_services/free_busy_service.py
gcsa/_services/settings_service.py
gcsa/serializers/__init__.py
gcsa/serializers/acl_rule_serializer.py
gcsa/serializers/attachment_serializer.py
gcsa/serializers/attendee_serializer.py
gcsa/serializers/base_serializer.py
gcsa/serializers/calendar_serializer.py
gcsa/serializers/conference_serializer.py
gcsa/serializers/event_serializer.py
gcsa/serializers/free_busy_serializer.py
gcsa/serializers/person_serializer.py
gcsa/serializers/reminder_serializer.py
gcsa/serializers/settings_serializer.py
gcsa/util/__init__.py
gcsa/util/date_time_util.py
gcsa/util/utils.py
gcsa-2.6.0.dist-info/licenses/LICENSE
gcsa-2.6.0.dist-info/METADATA
gcsa-2.6.0.dist-info/WHEEL
gcsa-2.6.0.dist-info/top_level.txt
gcsa-2.6.0.dist-info/RECORD
