Metadata-Version: 2.4
Name: gcsa
Version: 2.6.0
Summary: Simple API for Google Calendar management
Home-page: https://github.com/kuzmoyev/google-calendar-simple-api
Author: Yevhen Kuzmovych
Author-email: kuzmovych.yevhen@gmail.com
License: MIT
Keywords: python conference calendar hangouts python-library event conferences google-calendar pip recurrence google-calendar-api attendee gcsa
Classifier: License :: OSI Approved :: MIT License
Classifier: Natural Language :: English
Classifier: Programming Language :: Python
Classifier: Programming Language :: Python :: 3
Classifier: Programming Language :: Python :: 3.5
Classifier: Programming Language :: Python :: 3.6
Classifier: Programming Language :: Python :: 3.7
Classifier: Programming Language :: Python :: 3.8
Classifier: Programming Language :: Python :: 3.9
Classifier: Programming Language :: Python :: 3.10
Classifier: Programming Language :: Python :: 3.11
Classifier: Programming Language :: Python :: 3.12
Classifier: Programming Language :: Python :: 3.13
License-File: LICENSE
Requires-Dist: tzlocal<6,>=4
Requires-Dist: google-api-python-client>=1.8
Requires-Dist: google-auth-httplib2>=0.0.4
Requires-Dist: google-auth-oauthlib<2.0,>=0.5
Requires-Dist: python-dateutil>=2.7
Requires-Dist: beautiful_date>=2.0.0
Provides-Extra: dev
Requires-Dist: setuptools; extra == "dev"
Requires-Dist: pytest; extra == "dev"
Requires-Dist: pytest-pep8; extra == "dev"
Requires-Dist: pytest-cov; extra == "dev"
Requires-Dist: pyfakefs; extra == "dev"
Requires-Dist: flake8; extra == "dev"
Requires-Dist: pep8-naming; extra == "dev"
Requires-Dist: twine; extra == "dev"
Requires-Dist: tox; extra == "dev"
Requires-Dist: sphinx; extra == "dev"
Requires-Dist: sphinx-rtd-theme; extra == "dev"
Requires-Dist: sphinxcontrib-googleanalytics; extra == "dev"
Provides-Extra: tests
Requires-Dist: setuptools; extra == "tests"
Requires-Dist: pytest; extra == "tests"
Requires-Dist: pytest-pep8; extra == "tests"
Requires-Dist: pytest-cov; extra == "tests"
Requires-Dist: pyfakefs; extra == "tests"
Requires-Dist: flake8; extra == "tests"
Requires-Dist: pep8-naming; extra == "tests"
Requires-Dist: twine; extra == "tests"
Requires-Dist: tox; extra == "tests"
Provides-Extra: docs
Requires-Dist: sphinx; extra == "docs"
Requires-Dist: sphinx-rtd-theme; extra == "docs"
Requires-Dist: sphinxcontrib-googleanalytics; extra == "docs"
Dynamic: author
Dynamic: author-email
Dynamic: classifier
Dynamic: description
Dynamic: home-page
Dynamic: keywords
Dynamic: license
Dynamic: license-file
Dynamic: provides-extra
Dynamic: requires-dist
Dynamic: summary
